db/__init__.py
db/azure.py
db/db.py
http_params_hook/__init__.py
http_params_hook/http_params_hook.py
log_message_operator/__init__.py
log_message_operator/log_message_operator.py
path/__init__.py
path/path.py
sql/__init__.py
sql/sql.py
amsterdam_airflow_common-1.7.dist-info/METADATA
amsterdam_airflow_common-1.7.dist-info/WHEEL
amsterdam_airflow_common-1.7.dist-info/RECORD
